flappy_rl/__init__.py
flappy_rl/main.py
flappy_rl/assets/Screen Recording 2025-02-23 170420.gif
flappy_rl/assets/futuristic-robotic-hummingbird_23-2151443897-Photoroom.png
flappy_rl/assets/image (1).png
flappy_rl/game/__init__.py
flappy_rl/game/flappy_bird.py
flappy_rl/models/best_q_table_beginner.npy
flappy_rl/models/best_q_table_hard.npy
flappy_rl-0.2.3.dist-info/licenses/LICENSE
flappy_rl-0.2.3.dist-info/METADATA
flappy_rl-0.2.3.dist-info/WHEEL
flappy_rl-0.2.3.dist-info/entry_points.txt
flappy_rl-0.2.3.dist-info/top_level.txt
flappy_rl-0.2.3.dist-info/RECORD
