Metadata-Version: 2.4
Name: flappy_rl
Version: 0.2.3
Summary: FlappyBird game with Reinforcement Learning AI
Author-email: kaifeng-cmd <dreamkfeng@gmail.com>
License: MIT License
Project-URL: Homepage, https://github.com/kaifeng-cmd/zephyra
Project-URL: Bug Tracker, https://github.com/kaifeng-cmd/zephyra/issues
Classifier: Programming Language :: Python :: 3
Classifier: License :: OSI Approved :: MIT License
Classifier: Operating System :: OS Independent
Requires-Python: >=3.8
License-File: LICENSE
Requires-Dist: pygame>=2.0.0
Requires-Dist: numpy>=1.19.0
Requires-Dist: matplotlib>=3.3.0
Dynamic: license-file
